{"id":"maki-1975","constructorId":"maki","constructorName":"Maki","year":1975,"raceCount":14,"calendar":["Argentina","Brazil","South Africa","Spain","Monaco","Belgium","Sweden","Netherlands","France","Great Britain","Germany","Austria","Italy","United States"],"draftPool":{"drivers":[{"id":"hiroshi-fushida","name":"Hiroshi Fushida","rating":54,"stats":{"wins":0,"poles":0,"points":0,"avgFinish":0,"raceStarts":2},"ratingBreakdown":{"seasonForm":59,"yearPerformance":59,"careerPeakToDate":59,"seasonsToDate":1,"pointsTierCap":99,"teammateDelta":0,"teammateBaseline":0,"teammateNames":["Tony Trimmer"],"deltaPercentile":71,"computedRating":54,"raceStarts":2,"isOverridden":false}},{"id":"tony-trimmer","name":"Tony Trimmer","rating":54,"stats":{"wins":0,"poles":0,"points":0,"avgFinish":0,"raceStarts":3},"ratingBreakdown":{"seasonForm":59,"yearPerformance":59,"careerPeakToDate":59,"seasonsToDate":1,"pointsTierCap":99,"teammateDelta":0,"teammateBaseline":0,"teammateNames":["Hiroshi Fushida"],"deltaPercentile":71,"computedRating":54,"raceStarts":3,"isOverridden":false}}],"chassis":[{"id":"maki-f101c","name":"Maki F101c","rating":47,"meta":"Maki","ratingBreakdown":{"seasonForm":52,"teammateDelta":null,"teammateBaseline":null,"teammateNames":[],"deltaPercentile":null,"computedRating":47,"raceStarts":0,"isOverridden":false}}],"engines":[{"id":"ford-cosworth-dfv-30-v8","name":"Ford Cosworth DFV 3.0 V8","rating":85,"meta":"Ford","ratingBreakdown":{"seasonForm":99,"teammateDelta":null,"teammateBaseline":null,"teammateNames":[],"deltaPercentile":null,"computedRating":85,"raceStarts":0,"isOverridden":false}}],"teamPrincipals":[{"id":"tp-maki-1975","name":"Maki Team Principal","rating":40,"meta":"Team Principal"}],"pitTeams":[{"id":"pit-maki-1975","name":"Maki Pit Crew","rating":38,"meta":"Pit Crew"}],"devBudgets":[{"id":"budget-maki-1975","name":"Maki Development Budget","rating":32,"meta":"Minimal budget"}],"reserves":[{"id":"reserve-maki-1975","name":"Maki Reserve Driver","rating":30,"meta":"Reserve Driver"}]},"opponents":[{"id":"march","name":"March","strength":81},{"id":"fittipaldi","name":"Fittipaldi","strength":52},{"id":"hesketh","name":"Hesketh","strength":88},{"id":"tyrrell","name":"Tyrrell","strength":84},{"id":"lola","name":"Lola","strength":52},{"id":"hill","name":"Hill","strength":63},{"id":"penske","name":"Penske","strength":59},{"id":"frank-williams-racing-cars","name":"Frank Williams Racing Cars","strength":70},{"id":"ensign","name":"Ensign","strength":55},{"id":"lotus","name":"Lotus","strength":74},{"id":"mclaren","name":"McLaren","strength":95},{"id":"brabham","name":"Brabham","strength":92},{"id":"surtees","name":"Surtees","strength":52},{"id":"shadow","name":"Shadow","strength":77},{"id":"lyncar","name":"Lyncar","strength":52},{"id":"ferrari","name":"Ferrari","strength":99},{"id":"brm","name":"BRM","strength":52},{"id":"parnelli","name":"Parnelli","strength":66}],"historicalWccPosition":18}