{"id":"ensign-1974","constructorId":"ensign","constructorName":"Ensign","year":1974,"raceCount":15,"calendar":["Argentina","Brazil","South Africa","Spain","Belgium","Monaco","Sweden","Netherlands","France","Great Britain","Germany","Austria","Italy","Canada","United States"],"draftPool":{"drivers":[{"id":"rikky-von-opel","name":"Frederick von Opel","rating":54,"stats":{"wins":0,"poles":0,"points":0,"avgFinish":9,"raceStarts":7},"ratingBreakdown":{"seasonForm":59,"yearPerformance":59,"careerPeakToDate":59,"seasonsToDate":2,"pointsTierCap":99,"teammateDelta":0,"teammateBaseline":0,"teammateNames":["Vernon Schuppan"],"deltaPercentile":73,"computedRating":54,"raceStarts":7,"isOverridden":false}},{"id":"vern-schuppan","name":"Vernon Schuppan","rating":54,"stats":{"wins":0,"poles":0,"points":0,"avgFinish":15,"raceStarts":7},"ratingBreakdown":{"seasonForm":59,"yearPerformance":59,"careerPeakToDate":59,"seasonsToDate":1,"pointsTierCap":99,"teammateDelta":0,"teammateBaseline":0,"teammateNames":["Frederick von Opel"],"deltaPercentile":73,"computedRating":54,"raceStarts":7,"isOverridden":false}}],"chassis":[{"id":"ensign-n174","name":"Ensign N174","rating":53,"meta":"Ensign","ratingBreakdown":{"seasonForm":58,"teammateDelta":null,"teammateBaseline":null,"teammateNames":[],"deltaPercentile":null,"computedRating":53,"raceStarts":0,"isOverridden":false}}],"engines":[{"id":"ford-cosworth-dfv-30-v8","name":"Ford Cosworth DFV 3.0 V8","rating":85,"meta":"Ford","ratingBreakdown":{"seasonForm":99,"teammateDelta":null,"teammateBaseline":null,"teammateNames":[],"deltaPercentile":null,"computedRating":85,"raceStarts":0,"isOverridden":false}}],"teamPrincipals":[{"id":"tp-ensign-1974","name":"Ensign Team Principal","rating":42,"meta":"Team Principal"}],"pitTeams":[{"id":"pit-ensign-1974","name":"Ensign Pit Crew","rating":38,"meta":"Pit Crew"}],"devBudgets":[{"id":"budget-ensign-1974","name":"Ensign Development Budget","rating":32,"meta":"Minimal budget"}],"reserves":[{"id":"reserve-ensign-1974","name":"Ensign Reserve Driver","rating":30,"meta":"Reserve Driver"}]},"opponents":[{"id":"surtees","name":"Surtees","strength":65},{"id":"brabham","name":"Brabham","strength":85},{"id":"tyrrell","name":"Tyrrell","strength":92},{"id":"amon","name":"Amon","strength":58},{"id":"march","name":"March","strength":71},{"id":"lola","name":"Lola","strength":61},{"id":"iso-marlboro","name":"Iso-Marlboro","strength":68},{"id":"hesketh","name":"Hesketh","strength":82},{"id":"lotus","name":"Lotus","strength":89},{"id":"maki","name":"Maki","strength":58},{"id":"mclaren","name":"McLaren","strength":99},{"id":"brm","name":"BRM","strength":78},{"id":"penske","name":"Penske","strength":58},{"id":"lyncar","name":"Lyncar","strength":58},{"id":"ferrari","name":"Ferrari","strength":96},{"id":"token","name":"Token","strength":58},{"id":"trojan","name":"Trojan","strength":58},{"id":"shadow","name":"Shadow","strength":75},{"id":"parnelli","name":"Parnelli","strength":58}],"historicalWccPosition":13}