{"id":"brm-1957","constructorId":"brm","constructorName":"BRM","year":1957,"raceCount":8,"calendar":["Argentina","Monaco","Indianapolis","France","Great Britain","Germany","Pescara","Italy"],"draftPool":{"drivers":[{"id":"roy-salvadori","name":"Roy Francesco Salvadori","rating":74,"stats":{"wins":0,"poles":0,"points":2,"avgFinish":5,"raceStarts":5},"ratingBreakdown":{"seasonForm":68,"yearPerformance":69,"careerPeakToDate":68,"seasonsToDate":3,"pointsTierCap":99,"teammateDelta":2,"teammateBaseline":0,"teammateNames":["Ron Flockhart"],"deltaPercentile":85,"computedRating":74,"raceStarts":5,"isOverridden":false}},{"id":"ron-flockhart","name":"Ron Flockhart","rating":51,"stats":{"wins":0,"poles":0,"points":0,"avgFinish":0,"raceStarts":2},"ratingBreakdown":{"seasonForm":45,"yearPerformance":45,"careerPeakToDate":62,"seasonsToDate":3,"pointsTierCap":99,"teammateDelta":-2,"teammateBaseline":2,"teammateNames":["Roy Francesco Salvadori"],"deltaPercentile":44,"computedRating":51,"raceStarts":2,"isOverridden":false}}],"chassis":[{"id":"brm-p25","name":"Brm P25","rating":55,"meta":"BRM","ratingBreakdown":{"seasonForm":60,"teammateDelta":null,"teammateBaseline":null,"teammateNames":[],"deltaPercentile":null,"computedRating":55,"raceStarts":0,"isOverridden":false}}],"engines":[{"id":"brm-p25-25-l4","name":"BRM P25 2.5 L4","rating":46,"meta":"BRM","ratingBreakdown":{"seasonForm":51,"teammateDelta":null,"teammateBaseline":null,"teammateNames":[],"deltaPercentile":null,"computedRating":46,"raceStarts":0,"isOverridden":false}}],"teamPrincipals":[{"id":"tp-brm-1957","name":"BRM Team Principal","rating":58,"meta":"Team Principal"}],"pitTeams":[{"id":"pit-brm-1957","name":"BRM Pit Crew","rating":38,"meta":"Pit Crew"}],"devBudgets":[{"id":"budget-brm-1957","name":"BRM Development Budget","rating":43,"meta":"Minimal budget"}],"reserves":[{"id":"reserve-brm-1957","name":"BRM Reserve Driver","rating":30,"meta":"Reserve Driver"}]},"opponents":[{"id":"kuzma","name":"Kuzma","strength":74},{"id":"kurtis-kraft","name":"Kurtis Kraft","strength":79},{"id":"phillips","name":"Phillips","strength":60},{"id":"cooper","name":"Cooper","strength":65},{"id":"maserati","name":"Maserati","strength":99},{"id":"connaught","name":"Connaught","strength":69},{"id":"porsche","name":"Porsche","strength":60},{"id":"epperly","name":"Epperly","strength":84},{"id":"dunn","name":"Dunn","strength":60},{"id":"watson","name":"Watson","strength":60},{"id":"lesovsky","name":"Lesovsky","strength":60},{"id":"ferrari","name":"Ferrari","strength":89},{"id":"vanwall","name":"Vanwall","strength":94}],"historicalWccPosition":9}