{"id":"sauber-1994","constructorId":"sauber","constructorName":"Sauber","year":1994,"raceCount":16,"calendar":["Brazil","Pacific","San Marino","Monaco","Spain","Canada","France","Great Britain","Germany","Hungary","Belgium","Italy","Portugal","Europe","Japan","Australia"],"draftPool":{"drivers":[{"id":"heinz-harald-frentzen","name":"Heinz-Harald Frentzen","rating":61,"stats":{"wins":0,"poles":0,"points":7,"avgFinish":6,"raceStarts":16},"ratingBreakdown":{"seasonForm":66,"yearPerformance":66,"careerPeakToDate":66,"seasonsToDate":1,"pointsTierCap":99,"teammateDelta":3,"teammateBaseline":4,"teammateNames":["Karl Wendlinger"],"deltaPercentile":81,"computedRating":61,"raceStarts":16,"isOverridden":false}},{"id":"karl-wendlinger","name":"Karl Wendlinger","rating":58,"stats":{"wins":0,"poles":0,"points":4,"avgFinish":5,"raceStarts":4},"ratingBreakdown":{"seasonForm":49,"yearPerformance":49,"careerPeakToDate":70,"seasonsToDate":3,"pointsTierCap":99,"teammateDelta":-3,"teammateBaseline":7,"teammateNames":["Heinz-Harald Frentzen"],"deltaPercentile":50,"computedRating":58,"raceStarts":4,"isOverridden":false}}],"chassis":[{"id":"sauber-c13","name":"Sauber C13","rating":60,"meta":"Sauber","ratingBreakdown":{"seasonForm":65,"teammateDelta":null,"teammateBaseline":null,"teammateNames":[],"deltaPercentile":null,"computedRating":60,"raceStarts":0,"isOverridden":false}}],"engines":[{"id":"mercedes-benz-2175b-35-v10","name":"Mercedes-Benz 2175B 3.5 V10","rating":48,"meta":"Mercedes","ratingBreakdown":{"seasonForm":53,"teammateDelta":null,"teammateBaseline":null,"teammateNames":[],"deltaPercentile":null,"computedRating":48,"raceStarts":0,"isOverridden":false}}],"teamPrincipals":[{"id":"tp-sauber-1994","name":"Sauber Team Principal","rating":62,"meta":"Team Principal"}],"pitTeams":[{"id":"pit-sauber-1994","name":"Sauber Pit Crew","rating":47,"meta":"Pit Crew"}],"devBudgets":[{"id":"budget-sauber-1994","name":"Sauber Development Budget","rating":65,"meta":"Moderate budget"}],"reserves":[{"id":"reserve-sauber-1994","name":"Sauber Reserve Driver","rating":35,"meta":"Reserve Driver"}]},"opponents":[{"id":"footwork","name":"Footwork","strength":60},{"id":"ligier","name":"Ligier","strength":74},{"id":"mclaren","name":"McLaren","strength":84},{"id":"benetton","name":"Benetton","strength":94},{"id":"minardi","name":"Minardi","strength":55},{"id":"simtek","name":"Simtek","strength":45},{"id":"pacific","name":"Pacific","strength":45},{"id":"williams","name":"Williams","strength":99},{"id":"jordan","name":"Jordan","strength":79},{"id":"ferrari","name":"Ferrari","strength":89},{"id":"lotus","name":"Lotus","strength":45},{"id":"larrousse","name":"Larrousse","strength":50},{"id":"tyrrell","name":"Tyrrell","strength":74}],"historicalWccPosition":8}