{"id":"honda-1968","constructorId":"honda","constructorName":"Honda","year":1968,"raceCount":12,"calendar":["South Africa","Spain","Monaco","Belgium","Netherlands","France","Great Britain","Germany","Italy","Canada","United States","Mexico"],"draftPool":{"drivers":[{"id":"john-surtees","name":"John Surtees","rating":85,"stats":{"wins":0,"poles":1,"points":12,"avgFinish":4.5,"raceStarts":12},"ratingBreakdown":{"seasonForm":81,"yearPerformance":86,"careerPeakToDate":96,"seasonsToDate":8,"pointsTierCap":99,"teammateDelta":9,"teammateBaseline":3,"teammateNames":["Joakim Bonnier"],"deltaPercentile":99,"computedRating":85,"raceStarts":12,"isOverridden":false}},{"id":"jo-bonnier","name":"Joakim Bonnier","rating":51,"stats":{"wins":0,"poles":0,"points":3,"avgFinish":6.3,"raceStarts":9},"ratingBreakdown":{"seasonForm":43,"yearPerformance":40,"careerPeakToDate":65,"seasonsToDate":5,"pointsTierCap":99,"teammateDelta":-9,"teammateBaseline":12,"teammateNames":["John Surtees"],"deltaPercentile":43,"computedRating":51,"raceStarts":9,"isOverridden":false}}],"chassis":[{"id":"honda-ra300","name":"Honda Ra300","rating":56,"meta":"Honda","ratingBreakdown":{"seasonForm":61,"teammateDelta":null,"teammateBaseline":null,"teammateNames":[],"deltaPercentile":null,"computedRating":56,"raceStarts":0,"isOverridden":false}},{"id":"honda-ra301","name":"Honda Ra301","rating":56,"meta":"Honda","ratingBreakdown":{"seasonForm":61,"teammateDelta":null,"teammateBaseline":null,"teammateNames":[],"deltaPercentile":null,"computedRating":56,"raceStarts":0,"isOverridden":false}},{"id":"honda-ra302","name":"Honda Ra302","rating":56,"meta":"Honda","ratingBreakdown":{"seasonForm":61,"teammateDelta":null,"teammateBaseline":null,"teammateNames":[],"deltaPercentile":null,"computedRating":56,"raceStarts":0,"isOverridden":false}}],"engines":[{"id":"honda-ra273e-30-v12","name":"Honda RA273E 3.0 V12","rating":73,"meta":"Honda","ratingBreakdown":{"seasonForm":78,"teammateDelta":null,"teammateBaseline":null,"teammateNames":[],"deltaPercentile":null,"computedRating":73,"raceStarts":0,"isOverridden":false}},{"id":"honda-ra301e-30-v12","name":"Honda RA301E 3.0 V12","rating":73,"meta":"Honda","ratingBreakdown":{"seasonForm":78,"teammateDelta":null,"teammateBaseline":null,"teammateNames":[],"deltaPercentile":null,"computedRating":73,"raceStarts":0,"isOverridden":false}},{"id":"honda-ra302e-30-v8","name":"Honda RA302E 3.0 V8","rating":73,"meta":"Honda","ratingBreakdown":{"seasonForm":78,"teammateDelta":null,"teammateBaseline":null,"teammateNames":[],"deltaPercentile":null,"computedRating":73,"raceStarts":0,"isOverridden":false}}],"teamPrincipals":[{"id":"tp-honda-1968","name":"Honda Team Principal","rating":66,"meta":"Team Principal"}],"pitTeams":[{"id":"pit-honda-1968","name":"Honda Pit Crew","rating":43,"meta":"Pit Crew"}],"devBudgets":[{"id":"budget-honda-1968","name":"Honda Development Budget","rating":78,"meta":"Large budget"}],"reserves":[{"id":"reserve-honda-1968","name":"Honda Reserve Driver","rating":31,"meta":"Reserve Driver"}]},"opponents":[{"id":"eagle","name":"Eagle","strength":49},{"id":"mclaren","name":"McLaren","strength":93},{"id":"lola","name":"Lola","strength":49},{"id":"brm","name":"BRM","strength":74},{"id":"brabham","name":"Brabham","strength":55},{"id":"cooper","name":"Cooper","strength":68},{"id":"matra","name":"Matra","strength":86},{"id":"lotus","name":"Lotus","strength":99},{"id":"ferrari","name":"Ferrari","strength":80},{"id":"lds","name":"LDS","strength":49}],"historicalWccPosition":7}