{"id":"bmw-sauber-2009","constructorId":"bmw-sauber","constructorName":"BMW Sauber","year":2009,"raceCount":17,"calendar":["Australia","Malaysia","China","Bahrain","Spain","Monaco","Turkey","Great Britain","Germany","Hungary","Europe","Belgium","Italy","Singapore","Japan","Brazil","Abu Dhabi"],"draftPool":{"drivers":[{"id":"nick-heidfeld","name":"Nick Lars Heidfeld","rating":68,"stats":{"wins":0,"poles":0,"points":19,"avgFinish":9.5,"raceStarts":17},"ratingBreakdown":{"seasonForm":59,"yearPerformance":59,"careerPeakToDate":80,"seasonsToDate":10,"pointsTierCap":99,"teammateDelta":2,"teammateBaseline":17,"teammateNames":["Robert Józef Kubica"],"deltaPercentile":68,"computedRating":68,"raceStarts":17,"isOverridden":false}},{"id":"robert-kubica","name":"Robert Józef Kubica","rating":70,"stats":{"wins":0,"poles":0,"points":17,"avgFinish":10.3,"raceStarts":17},"ratingBreakdown":{"seasonForm":56,"yearPerformance":56,"careerPeakToDate":85,"seasonsToDate":3,"pointsTierCap":99,"teammateDelta":-2,"teammateBaseline":19,"teammateNames":["Nick Lars Heidfeld"],"deltaPercentile":65,"computedRating":70,"raceStarts":17,"isOverridden":false}}],"chassis":[{"id":"bmw-sauber-f1-09","name":"Bmw Sauber F1 09","rating":60,"meta":"BMW Sauber","ratingBreakdown":{"seasonForm":65,"teammateDelta":null,"teammateBaseline":null,"teammateNames":[],"deltaPercentile":null,"computedRating":60,"raceStarts":0,"isOverridden":false}}],"engines":[{"id":"bmw-p86-9-24-v8","name":"BMW P86/9 2.4 V8","rating":39,"meta":"BMW","ratingBreakdown":{"seasonForm":44,"teammateDelta":null,"teammateBaseline":null,"teammateNames":[],"deltaPercentile":null,"computedRating":39,"raceStarts":0,"isOverridden":false}}],"teamPrincipals":[{"id":"tp-bmw-sauber-2009","name":"BMW Sauber Team Principal","rating":70,"meta":"Team Principal"}],"pitTeams":[{"id":"pit-bmw-sauber-2009","name":"BMW Sauber Pit Crew","rating":65,"meta":"Pit Crew"}],"devBudgets":[{"id":"budget-bmw-sauber-2009","name":"BMW Sauber Development Budget","rating":54,"meta":"Limited budget"}],"reserves":[{"id":"reserve-bmw-sauber-2009","name":"BMW Sauber Reserve Driver","rating":35,"meta":"Reserve Driver"}]},"opponents":[{"id":"williams","name":"Williams","strength":58},{"id":"brawn","name":"Brawn","strength":99},{"id":"force-india","name":"Force India","strength":44},{"id":"renault","name":"Renault","strength":51},{"id":"toyota","name":"Toyota","strength":71},{"id":"red-bull","name":"Red Bull","strength":92},{"id":"ferrari","name":"Ferrari","strength":78},{"id":"toro-rosso","name":"Toro Rosso","strength":37},{"id":"mclaren","name":"McLaren","strength":85}],"historicalWccPosition":6}