{"id":"brabham-1972","constructorId":"brabham","constructorName":"Brabham","year":1972,"raceCount":12,"calendar":["Argentina","South Africa","Spain","Monaco","Belgium","France","Great Britain","Germany","Austria","Italy","Canada","United States"],"draftPool":{"drivers":[{"id":"graham-hill","name":"Norman Graham Hill","rating":81,"stats":{"wins":0,"poles":0,"points":4,"avgFinish":8.5,"raceStarts":12},"ratingBreakdown":{"seasonForm":61,"yearPerformance":62,"careerPeakToDate":99,"seasonsToDate":12,"pointsTierCap":99,"teammateDelta":1,"teammateBaseline":3,"teammateNames":["Carlos Alberto Reutemann"],"deltaPercentile":72,"computedRating":81,"raceStarts":12,"isOverridden":false}},{"id":"carlos-reutemann","name":"Carlos Alberto Reutemann","rating":49,"stats":{"wins":0,"poles":1,"points":3,"avgFinish":8.8,"raceStarts":10},"ratingBreakdown":{"seasonForm":54,"yearPerformance":54,"careerPeakToDate":54,"seasonsToDate":1,"pointsTierCap":99,"teammateDelta":-1,"teammateBaseline":4,"teammateNames":["Norman Graham Hill"],"deltaPercentile":61,"computedRating":49,"raceStarts":10,"isOverridden":false}}],"chassis":[{"id":"brabham-bt33","name":"Brabham Bt33","rating":52,"meta":"Brabham","ratingBreakdown":{"seasonForm":57,"teammateDelta":null,"teammateBaseline":null,"teammateNames":[],"deltaPercentile":null,"computedRating":52,"raceStarts":0,"isOverridden":false}},{"id":"brabham-bt34","name":"Brabham Bt34","rating":52,"meta":"Brabham","ratingBreakdown":{"seasonForm":57,"teammateDelta":null,"teammateBaseline":null,"teammateNames":[],"deltaPercentile":null,"computedRating":52,"raceStarts":0,"isOverridden":false}},{"id":"brabham-bt37","name":"Brabham Bt37","rating":52,"meta":"Brabham","ratingBreakdown":{"seasonForm":57,"teammateDelta":null,"teammateBaseline":null,"teammateNames":[],"deltaPercentile":null,"computedRating":52,"raceStarts":0,"isOverridden":false}}],"engines":[{"id":"ford-cosworth-dfv-30-v8","name":"Ford Cosworth DFV 3.0 V8","rating":85,"meta":"Ford","ratingBreakdown":{"seasonForm":99,"teammateDelta":null,"teammateBaseline":null,"teammateNames":[],"deltaPercentile":null,"computedRating":85,"raceStarts":0,"isOverridden":false}}],"teamPrincipals":[{"id":"tp-brabham-1972","name":"Brabham Team Principal","rating":58,"meta":"Team Principal"}],"pitTeams":[{"id":"pit-brabham-1972","name":"Brabham Pit Crew","rating":46,"meta":"Pit Crew"}],"devBudgets":[{"id":"budget-brabham-1972","name":"Brabham Development Budget","rating":43,"meta":"Minimal budget"}],"reserves":[{"id":"reserve-brabham-1972","name":"Brabham Reserve Driver","rating":30,"meta":"Reserve Driver"}]},"opponents":[{"id":"surtees","name":"Surtees","strength":72},{"id":"march","name":"March","strength":67},{"id":"connew","name":"Connew","strength":51},{"id":"tyrrell","name":"Tyrrell","strength":94},{"id":"matra","name":"Matra","strength":62},{"id":"lotus","name":"Lotus","strength":99},{"id":"brm","name":"BRM","strength":78},{"id":"tecno","name":"Tecno","strength":51},{"id":"ferrari","name":"Ferrari","strength":83},{"id":"eifelland","name":"Eifelland","strength":51},{"id":"politoys","name":"Politoys","strength":51},{"id":"mclaren","name":"McLaren","strength":88}],"historicalWccPosition":9}