{"id":"alfa-romeo-2020","constructorId":"alfa-romeo","constructorName":"Alfa Romeo","year":2020,"raceCount":17,"calendar":["Austria","Styria","Hungary","Great Britain","70th Anniversary","Spain","Belgium","Italy","Tuscany","Russia","Eifel","Portugal","Emilia Romagna","Turkey","Bahrain","Sakhir","Abu Dhabi"],"draftPool":{"drivers":[{"id":"antonio-giovinazzi","name":"Antonio Giovinazzi","rating":51,"stats":{"wins":0,"poles":0,"points":4,"avgFinish":13.9,"raceStarts":17},"ratingBreakdown":{"seasonForm":56,"yearPerformance":56,"careerPeakToDate":56,"seasonsToDate":3,"pointsTierCap":99,"teammateDelta":0,"teammateBaseline":4,"teammateNames":["Kimi-Matias Räikkönen"],"deltaPercentile":68,"computedRating":51,"raceStarts":17,"isOverridden":false}},{"id":"kimi-raikkonen","name":"Kimi-Matias Räikkönen","rating":79,"stats":{"wins":0,"poles":0,"points":4,"avgFinish":13,"raceStarts":17},"ratingBreakdown":{"seasonForm":56,"yearPerformance":56,"careerPeakToDate":99,"seasonsToDate":18,"pointsTierCap":99,"teammateDelta":0,"teammateBaseline":4,"teammateNames":["Antonio Giovinazzi"],"deltaPercentile":68,"computedRating":79,"raceStarts":17,"isOverridden":false}}],"chassis":[{"id":"alfa-romeo-c39","name":"Alfa Romeo C39","rating":46,"meta":"Alfa Romeo","ratingBreakdown":{"seasonForm":51,"teammateDelta":null,"teammateBaseline":null,"teammateNames":[],"deltaPercentile":null,"computedRating":46,"raceStarts":0,"isOverridden":false}}],"engines":[{"id":"ferrari-065-16-v6-t-h","name":"Ferrari 065 1.6 V6 T H","rating":39,"meta":"Ferrari","ratingBreakdown":{"seasonForm":44,"teammateDelta":null,"teammateBaseline":null,"teammateNames":[],"deltaPercentile":null,"computedRating":39,"raceStarts":0,"isOverridden":false}}],"teamPrincipals":[{"id":"tp-alfa-romeo-2020","name":"Alfa Romeo Team Principal","rating":62,"meta":"Team Principal"}],"pitTeams":[{"id":"pit-alfa-romeo-2020","name":"Alfa Romeo Pit Crew","rating":52,"meta":"Pit Crew"}],"devBudgets":[{"id":"budget-alfa-romeo-2020","name":"Alfa Romeo Development Budget","rating":46,"meta":"Limited budget"}],"reserves":[{"id":"robert-kubica","name":"Robert Józef Kubica","rating":30,"meta":"Reserve Driver"}]},"opponents":[{"id":"red-bull","name":"Red Bull","strength":92},{"id":"racing-point","name":"Racing Point","strength":85},{"id":"haas","name":"Haas","strength":44},{"id":"mclaren","name":"McLaren","strength":78},{"id":"mercedes","name":"Mercedes","strength":99},{"id":"renault","name":"Renault","strength":71},{"id":"alphatauri","name":"AlphaTauri","strength":58},{"id":"ferrari","name":"Ferrari","strength":65},{"id":"williams","name":"Williams","strength":37}],"historicalWccPosition":8}