{"id":"toro-rosso-2006","constructorId":"toro-rosso","constructorName":"Toro Rosso","year":2006,"raceCount":18,"calendar":["Bahrain","Malaysia","Australia","San Marino","Europe","Spain","Monaco","Great Britain","Canada","United States","France","Germany","Hungary","Turkey","Italy","China","Japan","Brazil"],"draftPool":{"drivers":[{"id":"vitantonio-liuzzi","name":"Vitantonio Liuzzi","rating":56,"stats":{"wins":0,"poles":0,"points":1,"avgFinish":12.1,"raceStarts":18},"ratingBreakdown":{"seasonForm":61,"yearPerformance":61,"careerPeakToDate":61,"seasonsToDate":1,"pointsTierCap":99,"teammateDelta":1,"teammateBaseline":0,"teammateNames":["Scott Andrew Speed"],"deltaPercentile":77,"computedRating":56,"raceStarts":18,"isOverridden":false}},{"id":"scott-speed","name":"Scott Andrew Speed","rating":43,"stats":{"wins":0,"poles":0,"points":0,"avgFinish":12.4,"raceStarts":18},"ratingBreakdown":{"seasonForm":48,"yearPerformance":48,"careerPeakToDate":48,"seasonsToDate":1,"pointsTierCap":99,"teammateDelta":-1,"teammateBaseline":1,"teammateNames":["Vitantonio Liuzzi"],"deltaPercentile":55,"computedRating":43,"raceStarts":18,"isOverridden":false}}],"chassis":[{"id":"toro-rosso-str1","name":"Toro Rosso Str1","rating":44,"meta":"Toro Rosso","ratingBreakdown":{"seasonForm":49,"teammateDelta":null,"teammateBaseline":null,"teammateNames":[],"deltaPercentile":null,"computedRating":44,"raceStarts":0,"isOverridden":false}}],"engines":[{"id":"cosworth-tj2006-30-v10","name":"Cosworth TJ2006 3.0 V10","rating":35,"meta":"Cosworth","ratingBreakdown":{"seasonForm":40,"teammateDelta":null,"teammateBaseline":null,"teammateNames":[],"deltaPercentile":null,"computedRating":35,"raceStarts":0,"isOverridden":false}}],"teamPrincipals":[{"id":"tp-toro-rosso-2006","name":"Toro Rosso Team Principal","rating":58,"meta":"Team Principal"}],"pitTeams":[{"id":"pit-toro-rosso-2006","name":"Toro Rosso Pit Crew","rating":46,"meta":"Pit Crew"}],"devBudgets":[{"id":"budget-toro-rosso-2006","name":"Toro Rosso Development Budget","rating":43,"meta":"Minimal budget"}],"reserves":[{"id":"neel-jani","name":"Neel Jani","rating":30,"meta":"Reserve Driver"}]},"opponents":[{"id":"bmw-sauber","name":"BMW Sauber","strength":74},{"id":"honda","name":"Honda","strength":80},{"id":"midland","name":"Midland","strength":43},{"id":"renault","name":"Renault","strength":93},{"id":"toyota","name":"Toyota","strength":68},{"id":"red-bull","name":"Red Bull","strength":61},{"id":"ferrari","name":"Ferrari","strength":99},{"id":"super-aguri","name":"Super Aguri","strength":43},{"id":"mclaren","name":"McLaren","strength":86},{"id":"williams","name":"Williams","strength":55}],"historicalWccPosition":9}