{"id":"dallara-1992","constructorId":"dallara","constructorName":"Dallara","year":1992,"raceCount":16,"calendar":["South Africa","Mexico","Brazil","Spain","San Marino","Monaco","Canada","France","Great Britain","Germany","Hungary","Belgium","Italy","Portugal","Japan","Australia"],"draftPool":{"drivers":[{"id":"pierluigi-martini","name":"Pierluigi Martini","rating":75,"stats":{"wins":0,"poles":0,"points":2,"avgFinish":9.3,"raceStarts":16},"ratingBreakdown":{"seasonForm":68,"yearPerformance":70,"careerPeakToDate":72,"seasonsToDate":6,"pointsTierCap":99,"teammateDelta":2,"teammateBaseline":0,"teammateNames":["Jyrki Juhani Järvilehto"],"deltaPercentile":86,"computedRating":75,"raceStarts":16,"isOverridden":false}},{"id":"jj-lehto","name":"Jyrki Juhani Järvilehto","rating":55,"stats":{"wins":0,"poles":0,"points":0,"avgFinish":9.5,"raceStarts":16},"ratingBreakdown":{"seasonForm":44,"yearPerformance":42,"careerPeakToDate":70,"seasonsToDate":3,"pointsTierCap":99,"teammateDelta":-2,"teammateBaseline":2,"teammateNames":["Pierluigi Martini"],"deltaPercentile":43,"computedRating":55,"raceStarts":16,"isOverridden":false}}],"chassis":[{"id":"dallara-f192","name":"Dallara F192","rating":55,"meta":"Dallara","ratingBreakdown":{"seasonForm":60,"teammateDelta":null,"teammateBaseline":null,"teammateNames":[],"deltaPercentile":null,"computedRating":55,"raceStarts":0,"isOverridden":false}}],"engines":[{"id":"ferrari-037-35-v12","name":"Ferrari 037 3.5 V12","rating":71,"meta":"Ferrari","ratingBreakdown":{"seasonForm":76,"teammateDelta":null,"teammateBaseline":null,"teammateNames":[],"deltaPercentile":null,"computedRating":71,"raceStarts":0,"isOverridden":false}}],"teamPrincipals":[{"id":"tp-dallara-1992","name":"Dallara Team Principal","rating":54,"meta":"Team Principal"}],"pitTeams":[{"id":"pit-dallara-1992","name":"Dallara Pit Crew","rating":51,"meta":"Pit Crew"}],"devBudgets":[{"id":"budget-dallara-1992","name":"Dallara Development Budget","rating":38,"meta":"Minimal budget"}],"reserves":[{"id":"reserve-dallara-1992","name":"Dallara Reserve Driver","rating":30,"meta":"Reserve Driver"}]},"opponents":[{"id":"andrea-moda","name":"Andrea Moda","strength":43},{"id":"benetton","name":"Benetton","strength":90},{"id":"williams","name":"Williams","strength":99},{"id":"venturi","name":"Venturi","strength":56},{"id":"fondmetal","name":"Fondmetal","strength":43},{"id":"footwork","name":"Footwork","strength":73},{"id":"mclaren","name":"McLaren","strength":95},{"id":"ligier","name":"Ligier","strength":73},{"id":"march","name":"March","strength":65},{"id":"minardi","name":"Minardi","strength":56},{"id":"brabham","name":"Brabham","strength":43},{"id":"jordan","name":"Jordan","strength":56},{"id":"ferrari","name":"Ferrari","strength":86},{"id":"lotus","name":"Lotus","strength":82},{"id":"tyrrell","name":"Tyrrell","strength":77}],"historicalWccPosition":10}